change_analyzer/__init__.py
change_analyzer/main.py
change_analyzer/sequences_diff.py
change_analyzer/utils.py
change_analyzer/agents/__init__.py
change_analyzer/agents/agent.py
change_analyzer/agents/explorer_agent.py
change_analyzer/agents/random_agent.py
change_analyzer/agents/replay_agent.py
change_analyzer/agents/strategy_agent.py
change_analyzer/envs/__init__.py
change_analyzer/envs/app_env.py
change_analyzer/envs/web_driver_env.py
change_analyzer/spaces/__init__.py
change_analyzer/spaces/discrete_app_action_space.py
change_analyzer/spaces/actions/__init__.py
change_analyzer/spaces/actions/app_action.py
change_analyzer/spaces/actions/click_app_action.py
change_analyzer/spaces/actions/form_app_action.py
change_analyzer/spaces/actions/input_app_action.py
change_analyzer/templates/Log_template.html
change_analyzer/tests/400x400.png
change_analyzer/tests/__init__.py
change_analyzer/tests/test_utils.py
change_analyzer/wrappers/__init__.py
change_analyzer/wrappers/enhanced_monitor.py
change_analyzer/wrappers/sequence_recorder.py
change_analyzer/wrappers/transparent_wrapper_mixin.py
change_analyzer-0.16.1.dist-info/METADATA
change_analyzer-0.16.1.dist-info/WHEEL
change_analyzer-0.16.1.dist-info/entry_points.txt
change_analyzer-0.16.1.dist-info/top_level.txt
change_analyzer-0.16.1.dist-info/RECORD
