Metadata-Version: 2.1
Name: change-analyzer
Version: 0.16.1
Summary: Change analyzer
Home-page: https://github.com/F-Secure/change-analyzer
Author: Matvey Pashkovskiy, Sorin Patrasoiu, Joona Oikarinen
Author-email: 
Platform: any
Classifier: Programming Language :: Python
Classifier: Programming Language :: Python :: 3
Classifier: Programming Language :: Python :: 3.7
Classifier: Programming Language :: Python :: 3.8
Classifier: Programming Language :: Python :: 3.9
Requires-Dist: gym (==0.19.0)
Requires-Dist: appium-python-client (==1.0.2)
Requires-Dist: Pillow
Requires-Dist: pywinauto
Requires-Dist: selenium
Requires-Dist: faker
Requires-Dist: jinja2
Requires-Dist: pandas
Requires-Dist: numpy
Requires-Dist: matplotlib
Requires-Dist: xmldiff
Requires-Dist: beautifulsoup4
Requires-Dist: lxml
Requires-Dist: ludwig (==0.5.5)
Requires-Dist: torch (==1.11.0)
Requires-Dist: torchaudio (==0.11.0)
Requires-Dist: torchinfo (==1.7.0)
Requires-Dist: torchmetrics (==0.8.2)
Requires-Dist: torchtext (==0.12.0)
Requires-Dist: torchvision (==0.12.0)
Requires-Dist: petastorm (==0.11.3)
Requires-Dist: ludwig[viz]
Requires-Dist: ludwig[image]
Provides-Extra: dev
Requires-Dist: black ; extra == 'dev'
Requires-Dist: jupyterlab ; extra == 'dev'
Requires-Dist: pytest (==6.2.5) ; extra == 'dev'
Requires-Dist: python-semantic-release ; extra == 'dev'
Requires-Dist: twine ; extra == 'dev'
Requires-Dist: wheel ; extra == 'dev'
Requires-Dist: xenon ; extra == 'dev'
